[{
  "_id": {
    "$oid": "684aca5df3433021c33dcbd7"
  },
  "user": {
    "$oid": "684aca5df3433021c33dc8e6"
  },
  "fullName": "Trần Thị Bình",
  "phone": "0996933926",
  "addressLine": "478 Đường 4",
  "city": "Hải Phòng",
  "district": "Long Biên",
  "ward": "Phường Thành Công",
  "isDefault": true,
  "createdAt": {
    "$date": "2025-06-03T21:59:11.786Z"
  },
  "updatedAt": {
    "$date": "2025-06-12T12:38:53.785Z"
  },
  "__v": 0
},
{
  "_id": {
    "$oid": "684aca5df3433021c33dcbd8"
  },
  "user": {
    "$oid": "684aca5df3433021c33dc8e7"
  },
  "fullName": "Lê Hoàng Cường",
  "phone": "0965208500",
  "addressLine": "963 Đường 11",
  "city": "Huế",
  "district": "Ba Đình",
  "ward": "Phường Thành Công",
  "isDefault": true,
  "createdAt": {
    "$date": "2024-06-19T14:35:37.328Z"
  },
  "updatedAt": {
    "$date": "2025-06-12T12:38:53.785Z"
  },
  "__v": 0
},
{
  "_id": {
    "$oid": "684aca5df3433021c33dcbd9"
  },
  "user": {
    "$oid": "684aca5df3433021c33dc8e8"
  },
  "fullName": "Phạm Thị Dương",
  "phone": "0947472030",
  "addressLine": "496 Đường 33",
  "city": "Đà Nẵng",
  "district": "Quận 1",
  "ward": "Phường 3",
  "isDefault": true,
  "createdAt": {
    "$date": "2024-12-01T03:09:21.559Z"
  },
  "updatedAt": {
    "$date": "2025-06-12T12:38:53.785Z"
  },
  "__v": 0
},
{
  "_id": {
    "$oid": "684aca5df3433021c33dcbda"
  },
  "user": {
    "$oid": "684aca5df3433021c33dc8e8"
  },
  "fullName": "Phạm Thị Dương",
  "phone": "0947472030",
  "addressLine": "432 Đường 6",
  "city": "Huế",
  "district": "Ba Đình",
  "ward": "Phường 1",
  "isDefault": false,
  "createdAt": {
    "$date": "2024-12-01T03:09:21.559Z"
  },
  "updatedAt": {
    "$date": "2025-06-12T12:38:53.785Z"
  },
  "__v": 0
},
{
  "_id": {
    "$oid": "684aca5df3433021c33dcbdb"
  },
  "user": {
    "$oid": "684aca5df3433021c33dc8e9"
  },
  "fullName": "Hoàng Văn Em",
  "phone": "0991784676",
  "addressLine": "487 Đường 5",
  "city": "Đà Nẵng",
  "district": "Ba Đình",
  "ward": "Phường 1",
  "isDefault": true,
  "createdAt": {
    "$date": "2025-02-21T22:11:14.589Z"
  },
  "updatedAt": {
    "$date": "2025-06-12T12:38:53.785Z"
  },
  "__v": 0
},
{
  "_id": {
    "$oid": "684aca5df3433021c33dcbdc"
  },
  "user": {
    "$oid": "684aca5df3433021c33dc8e9"
  },
  "fullName": "Hoàng Văn Em",
  "phone": "0991784676",
  "addressLine": "858 Đường 11",
  "city": "Vũng Tàu",
  "district": "Quận 1",
  "ward": "Phường Thành Công",
  "isDefault": false,
  "createdAt": {
    "$date": "2025-02-21T22:11:14.589Z"
  },
  "updatedAt": {
    "$date": "2025-06-12T12:38:53.785Z"
  },
  "__v": 0
},
{
  "_id": {
    "$oid": "684aca5df3433021c33dcbdd"
  },
  "user": {
    "$oid": "684aca5df3433021c33dc8ea"
  },
  "fullName": "Ngô Thị Phương",
  "phone": "0972471384",
  "addressLine": "209 Đường 9",
  "city": "Hà Nội",
  "district": "Hoàn Kiếm",
  "ward": "Phường Láng Thượng",
  "isDefault": true,
  "createdAt": {
    "$date": "2024-12-01T16:04:04.898Z"
  },
  "updatedAt": {
    "$date": "2025-06-12T12:38:53.785Z"
  },
  "__v": 0
},
{
  "_id": {
    "$oid": "684aca5df3433021c33dcbde"
  },
  "user": {
    "$oid": "684aca5df3433021c33dc8eb"
  },
  "fullName": "Đặng Văn Giang",
  "phone": "0936512292",
  "addressLine": "596 Đường 17",
  "city": "Hải Phòng",
  "district": "Hoàn Kiếm",
  "ward": "Phường 2",
  "isDefault": true,
  "createdAt": {
    "$date": "2025-02-02T07:29:47.605Z"
  },
  "updatedAt": {
    "$date": "2025-06-12T12:38:53.785Z"
  },
  "__v": 0
},
{
  "_id": {
    "$oid": "684aca5df3433021c33dcbdf"
  },
  "user": {
    "$oid": "684aca5df3433021c33dc8eb"
  },
  "fullName": "Đặng Văn Giang",
  "phone": "0936512292",
  "addressLine": "515 Đường 20",
  "city": "Nha Trang",
  "district": "Quận 1",
  "ward": "Phường 2",
  "isDefault": false,
  "createdAt": {
    "$date": "2025-02-02T07:29:47.605Z"
  },
  "updatedAt": {
    "$date": "2025-06-12T12:38:53.785Z"
  },
  "__v": 0
},
{
  "_id": {
    "$oid": "684aca5df3433021c33dcbe0"
  },
  "user": {
    "$oid": "684aca5df3433021c33dc8ec"
  },
  "fullName": "Bùi Thị Hương",
  "phone": "0985366324",
  "addressLine": "137 Đường 36",
  "city": "Hải Phòng",
  "district": "Quận 2",
  "ward": "Phường 3",
  "isDefault": true,
  "createdAt": {
    "$date": "2024-10-04T05:16:17.626Z"
  },
  "updatedAt": {
    "$date": "2025-06-12T12:38:53.785Z"
  },
  "__v": 0
},
{
  "_id": {
    "$oid": "684aca5df3433021c33dcbe1"
  },
  "user": {
    "$oid": "684aca5df3433021c33dc8ec"
  },
  "fullName": "Bùi Thị Hương",
  "phone": "0985366324",
  "addressLine": "817 Đường 36",
  "city": "Hải Phòng",
  "district": "Quận 1",
  "ward": "Phường 1",
  "isDefault": false,
  "createdAt": {
    "$date": "2024-10-04T05:16:17.626Z"
  },
  "updatedAt": {
    "$date": "2025-06-12T12:38:53.785Z"
  },
  "__v": 0
},
{
  "_id": {
    "$oid": "684aca5df3433021c33dcbe2"
  },
  "user": {
    "$oid": "684aca5df3433021c33dc8ed"
  },
  "fullName": "Vũ Văn Inh",
  "phone": "0970179548",
  "addressLine": "196 Đường 10",
  "city": "Hải Phòng",
  "district": "Ba Đình",
  "ward": "Phường Quán Thánh",
  "isDefault": true,
  "createdAt": {
    "$date": "2025-03-26T14:42:48.490Z"
  },
  "updatedAt": {
    "$date": "2025-06-12T12:38:53.785Z"
  },
  "__v": 0
},
{
  "_id": {
    "$oid": "684aca5df3433021c33dcbe3"
  },
  "user": {
    "$oid": "684aca5df3433021c33dc8ee"
  },
  "fullName": "Cao Thị Khánh",
  "phone": "0964285556",
  "addressLine": "201 Đường 30",
  "city": "Hải Phòng",
  "district": "Hai Bà Trưng",
  "ward": "Phường Quán Thánh",
  "isDefault": true,
  "createdAt": {
    "$date": "2024-09-25T02:31:47.432Z"
  },
  "updatedAt": {
    "$date": "2025-06-12T12:38:53.785Z"
  },
  "__v": 0
},
{
  "_id": {
    "$oid": "684aca5df3433021c33dcbe4"
  },
  "user": {
    "$oid": "684aca5df3433021c33dc8ee"
  },
  "fullName": "Cao Thị Khánh",
  "phone": "0964285556",
  "addressLine": "988 Đường 32",
  "city": "Cần Thơ",
  "district": "Quận 3",
  "ward": "Phường Láng Thượng",
  "isDefault": false,
  "createdAt": {
    "$date": "2024-09-25T02:31:47.432Z"
  },
  "updatedAt": {
    "$date": "2025-06-12T12:38:53.785Z"
  },
  "__v": 0
},
{
  "_id": {
    "$oid": "684aca5df3433021c33dcbe5"
  },
  "user": {
    "$oid": "684aca5df3433021c33dc8ef"
  },
  "fullName": "Đỗ Văn Long",
  "phone": "0970702775",
  "addressLine": "536 Đường 33",
  "city": "Nha Trang",
  "district": "Quận 1",
  "ward": "Phường Quán Thánh",
  "isDefault": true,
  "createdAt": {
    "$date": "2024-11-27T21:42:24.418Z"
  },
  "updatedAt": {
    "$date": "2025-06-12T12:38:53.785Z"
  },
  "__v": 0
},
{
  "_id": {
    "$oid": "684aca5df3433021c33dcbe6"
  },
  "user": {
    "$oid": "684aca5df3433021c33dc8ef"
  },
  "fullName": "Đỗ Văn Long",
  "phone": "0970702775",
  "addressLine": "947 Đường 37",
  "city": "Hải Phòng",
  "district": "Long Biên",
  "ward": "Phường Thành Công",
  "isDefault": false,
  "createdAt": {
    "$date": "2024-11-27T21:42:24.418Z"
  },
  "updatedAt": {
    "$date": "2025-06-12T12:38:53.785Z"
  },
  "__v": 0
},
{
  "_id": {
    "$oid": "684aca5df3433021c33dcbe7"
  },
  "user": {
    "$oid": "684aca5df3433021c33dc8f0"
  },
  "fullName": "Lý Thị Minh",
  "phone": "0929271223",
  "addressLine": "665 Đường 34",
  "city": "Vũng Tàu",
  "district": "Ba Đình",
  "ward": "Phường 3",
  "isDefault": true,
  "createdAt": {
    "$date": "2025-03-20T13:36:32.496Z"
  },
  "updatedAt": {
    "$date": "2025-06-12T12:38:53.785Z"
  },
  "__v": 0
},
{
  "_id": {
    "$oid": "684aca5df3433021c33dcbe8"
  },
  "user": {
    "$oid": "684aca5df3433021c33dc8f0"
  },
  "fullName": "Lý Thị Minh",
  "phone": "0929271223",
  "addressLine": "865 Đường 41",
  "city": "Hồ Chí Minh",
  "district": "Hoàn Kiếm",
  "ward": "Phường 1",
  "isDefault": false,
  "createdAt": {
    "$date": "2025-03-20T13:36:32.496Z"
  },
  "updatedAt": {
    "$date": "2025-06-12T12:38:53.785Z"
  },
  "__v": 0
},
{
  "_id": {
    "$oid": "684aca5df3433021c33dcbe9"
  },
  "user": {
    "$oid": "684aca5df3433021c33dc8f1"
  },
  "fullName": "Tôn Văn Nam",
  "phone": "0982249991",
  "addressLine": "191 Đường 3",
  "city": "Nha Trang",
  "district": "Hoàn Kiếm",
  "ward": "Phường 1",
  "isDefault": true,
  "createdAt": {
    "$date": "2024-07-10T11:51:29.205Z"
  },
  "updatedAt": {
    "$date": "2025-06-12T12:38:53.785Z"
  },
  "__v": 0
},
{
  "_id": {
    "$oid": "684aca5df3433021c33dcbea"
  },
  "user": {
    "$oid": "684aca5df3433021c33dc8f1"
  },
  "fullName": "Tôn Văn Nam",
  "phone": "0982249991",
  "addressLine": "596 Đường 37",
  "city": "Hồ Chí Minh",
  "district": "Quận 1",
  "ward": "Phường Quán Thánh",
  "isDefault": false,
  "createdAt": {
    "$date": "2024-07-10T11:51:29.205Z"
  },
  "updatedAt": {
    "$date": "2025-06-12T12:38:53.785Z"
  },
  "__v": 0
},
{
  "_id": {
    "$oid": "684aca5df3433021c33dcbeb"
  },
  "user": {
    "$oid": "684aca5df3433021c33dc8f2"
  },
  "fullName": "Phan Thị Oanh",
  "phone": "0919103479",
  "addressLine": "945 Đường 13",
  "city": "Huế",
  "district": "Hai Bà Trưng",
  "ward": "Phường 3",
  "isDefault": true,
  "createdAt": {
    "$date": "2025-01-13T22:10:36.207Z"
  },
  "updatedAt": {
    "$date": "2025-06-12T12:38:53.785Z"
  },
  "__v": 0
},
{
  "_id": {
    "$oid": "684aca5df3433021c33dcbec"
  },
  "user": {
    "$oid": "684aca5df3433021c33dc8f2"
  },
  "fullName": "Phan Thị Oanh",
  "phone": "0919103479",
  "addressLine": "49 Đường 47",
  "city": "Nha Trang",
  "district": "Long Biên",
  "ward": "Phường 3",
  "isDefault": false,
  "createdAt": {
    "$date": "2025-01-13T22:10:36.207Z"
  },
  "updatedAt": {
    "$date": "2025-06-12T12:38:53.785Z"
  },
  "__v": 0
},
{
  "_id": {
    "$oid": "684aca5df3433021c33dcbed"
  },
  "user": {
    "$oid": "684aca5df3433021c33dc8f3"
  },
  "fullName": "Đinh Văn Phúc",
  "phone": "0951806181",
  "addressLine": "575 Đường 3",
  "city": "Nha Trang",
  "district": "Quận 3",
  "ward": "Phường Thành Công",
  "isDefault": true,
  "createdAt": {
    "$date": "2024-09-16T23:44:50.520Z"
  },
  "updatedAt": {
    "$date": "2025-06-12T12:38:53.785Z"
  },
  "__v": 0
},
{
  "_id": {
    "$oid": "684aca5df3433021c33dcbee"
  },
  "user": {
    "$oid": "684aca5df3433021c33dc8f4"
  },
  "fullName": "Võ Thị Quỳnh",
  "phone": "0932334969",
  "addressLine": "574 Đường 37",
  "city": "Hà Nội",
  "district": "Cầu Giấy",
  "ward": "Phường Láng Thượng",
  "isDefault": true,
  "createdAt": {
    "$date": "2025-01-22T22:11:43.524Z"
  },
  "updatedAt": {
    "$date": "2025-06-12T12:38:53.785Z"
  },
  "__v": 0
},
{
  "_id": {
    "$oid": "684aca5df3433021c33dcbef"
  },
  "user": {
    "$oid": "684aca5df3433021c33dc8f4"
  },
  "fullName": "Võ Thị Quỳnh",
  "phone": "0932334969",
  "addressLine": "406 Đường 4",
  "city": "Hải Phòng",
  "district": "Quận 3",
  "ward": "Phường 2",
  "isDefault": false,
  "createdAt": {
    "$date": "2025-01-22T22:11:43.524Z"
  },
  "updatedAt": {
    "$date": "2025-06-12T12:38:53.785Z"
  },
  "__v": 0
},
{
  "_id": {
    "$oid": "684aca5df3433021c33dcbf0"
  },
  "user": {
    "$oid": "684aca5df3433021c33dc8f5"
  },
  "fullName": "Dương Văn Sơn",
  "phone": "0998249840",
  "addressLine": "112 Đường 8",
  "city": "Nha Trang",
  "district": "Quận 1",
  "ward": "Phường 3",
  "isDefault": true,
  "createdAt": {
    "$date": "2025-02-05T19:07:58.973Z"
  },
  "updatedAt": {
    "$date": "2025-06-12T12:38:53.785Z"
  },
  "__v": 0
},
{
  "_id": {
    "$oid": "684aca5df3433021c33dcbf1"
  },
  "user": {
    "$oid": "684aca5df3433021c33dc8f6"
  },
  "fullName": "Chu Thị Tâm",
  "phone": "0918368804",
  "addressLine": "511 Đường 25",
  "city": "Hải Phòng",
  "district": "Long Biên",
  "ward": "Phường 1",
  "isDefault": true,
  "createdAt": {
    "$date": "2025-05-08T18:29:01.553Z"
  },
  "updatedAt": {
    "$date": "2025-06-12T12:38:53.785Z"
  },
  "__v": 0
},
{
  "_id": {
    "$oid": "684aca5df3433021c33dcbf2"
  },
  "user": {
    "$oid": "684aca5df3433021c33dc8f7"
  },
  "fullName": "Lưu Văn Ưng",
  "phone": "0937154781",
  "addressLine": "938 Đường 20",
  "city": "Huế",
  "district": "Quận 2",
  "ward": "Phường 1",
  "isDefault": true,
  "createdAt": {
    "$date": "2025-01-20T22:01:42.752Z"
  },
  "updatedAt": {
    "$date": "2025-06-12T12:38:53.785Z"
  },
  "__v": 0
},
{
  "_id": {
    "$oid": "684aca5df3433021c33dcbf3"
  },
  "user": {
    "$oid": "684aca5df3433021c33dc8f8"
  },
  "fullName": "Mai Thị Vân",
  "phone": "0934089989",
  "addressLine": "200 Đường 44",
  "city": "Đà Nẵng",
  "district": "Ba Đình",
  "ward": "Phường Thành Công",
  "isDefault": true,
  "createdAt": {
    "$date": "2025-02-15T16:36:48.869Z"
  },
  "updatedAt": {
    "$date": "2025-06-12T12:38:53.786Z"
  },
  "__v": 0
},
{
  "_id": {
    "$oid": "684aca5df3433021c33dcbf4"
  },
  "user": {
    "$oid": "684aca5df3433021c33dc8f9"
  },
  "fullName": "Trịnh Văn Xuân",
  "phone": "0919419004",
  "addressLine": "16 Đường 43",
  "city": "Vũng Tàu",
  "district": "Hai Bà Trưng",
  "ward": "Phường Thành Công",
  "isDefault": true,
  "createdAt": {
    "$date": "2025-04-08T11:31:03.995Z"
  },
  "updatedAt": {
    "$date": "2025-06-12T12:38:53.786Z"
  },
  "__v": 0
},
{
  "_id": {
    "$oid": "684aca5df3433021c33dcbf5"
  },
  "user": {
    "$oid": "684aca5df3433021c33dc8f9"
  },
  "fullName": "Trịnh Văn Xuân",
  "phone": "0919419004",
  "addressLine": "496 Đường 15",
  "city": "Nha Trang",
  "district": "Quận 3",
  "ward": "Phường 3",
  "isDefault": false,
  "createdAt": {
    "$date": "2025-04-08T11:31:03.995Z"
  },
  "updatedAt": {
    "$date": "2025-06-12T12:38:53.786Z"
  },
  "__v": 0
},
{
  "_id": {
    "$oid": "684aca5df3433021c33dcbf6"
  },
  "user": {
    "$oid": "684aca5df3433021c33dc8fa"
  },
  "fullName": "Hồ Thị Yến",
  "phone": "0976820718",
  "addressLine": "995 Đường 1",
  "city": "Nha Trang",
  "district": "Cầu Giấy",
  "ward": "Phường 3",
  "isDefault": true,
  "createdAt": {
    "$date": "2025-06-05T22:23:30.335Z"
  },
  "updatedAt": {
    "$date": "2025-06-12T12:38:53.786Z"
  },
  "__v": 0
},
{
  "_id": {
    "$oid": "684aca5df3433021c33dcbf7"
  },
  "user": {
    "$oid": "684aca5df3433021c33dc8fa"
  },
  "fullName": "Hồ Thị Yến",
  "phone": "0976820718",
  "addressLine": "759 Đường 38",
  "city": "Cần Thơ",
  "district": "Ba Đình",
  "ward": "Phường Quán Thánh",
  "isDefault": false,
  "createdAt": {
    "$date": "2025-06-05T22:23:30.335Z"
  },
  "updatedAt": {
    "$date": "2025-06-12T12:38:53.786Z"
  },
  "__v": 0
},
{
  "_id": {
    "$oid": "684aca5df3433021c33dcbf8"
  },
  "user": {
    "$oid": "684aca5df3433021c33dc8fb"
  },
  "fullName": "Lâm Văn Zung",
  "phone": "0963338786",
  "addressLine": "912 Đường 22",
  "city": "Hải Phòng",
  "district": "Ba Đình",
  "ward": "Phường 2",
  "isDefault": true,
  "createdAt": {
    "$date": "2025-05-18T01:35:39.666Z"
  },
  "updatedAt": {
    "$date": "2025-06-12T12:38:53.786Z"
  },
  "__v": 0
},
{
  "_id": {
    "$oid": "684aca5df3433021c33dcbf9"
  },
  "user": {
    "$oid": "684aca5df3433021c33dc8fb"
  },
  "fullName": "Lâm Văn Zung",
  "phone": "0963338786",
  "addressLine": "363 Đường 27",
  "city": "Đà Nẵng",
  "district": "Long Biên",
  "ward": "Phường Láng Thượng",
  "isDefault": false,
  "createdAt": {
    "$date": "2025-05-18T01:35:39.666Z"
  },
  "updatedAt": {
    "$date": "2025-06-12T12:38:53.786Z"
  },
  "__v": 0
},
{
  "_id": {
    "$oid": "684aca5df3433021c33dcbfa"
  },
  "user": {
    "$oid": "684aca5df3433021c33dc8fc"
  },
  "fullName": "Từ Thị Ánh",
  "phone": "0933521972",
  "addressLine": "717 Đường 29",
  "city": "Huế",
  "district": "Hai Bà Trưng",
  "ward": "Phường Thành Công",
  "isDefault": true,
  "createdAt": {
    "$date": "2025-04-22T13:24:06.789Z"
  },
  "updatedAt": {
    "$date": "2025-06-12T12:38:53.786Z"
  },
  "__v": 0
},
{
  "_id": {
    "$oid": "684aca5df3433021c33dcbfb"
  },
  "user": {
    "$oid": "684aca5df3433021c33dc8fc"
  },
  "fullName": "Từ Thị Ánh",
  "phone": "0933521972",
  "addressLine": "608 Đường 35",
  "city": "Hà Nội",
  "district": "Hai Bà Trưng",
  "ward": "Phường Láng Thượng",
  "isDefault": false,
  "createdAt": {
    "$date": "2025-04-22T13:24:06.789Z"
  },
  "updatedAt": {
    "$date": "2025-06-12T12:38:53.786Z"
  },
  "__v": 0
},
{
  "_id": {
    "$oid": "684aca5df3433021c33dcbfc"
  },
  "user": {
    "$oid": "684aca5df3433021c33dc8fd"
  },
  "fullName": "Quan Văn Bảo",
  "phone": "0992617900",
  "addressLine": "402 Đường 1",
  "city": "Vũng Tàu",
  "district": "Quận 1",
  "ward": "Phường Láng Thượng",
  "isDefault": true,
  "createdAt": {
    "$date": "2024-08-29T10:05:58.844Z"
  },
  "updatedAt": {
    "$date": "2025-06-12T12:38:53.786Z"
  },
  "__v": 0
},
{
  "_id": {
    "$oid": "684aca5df3433021c33dcbfd"
  },
  "user": {
    "$oid": "684aca5df3433021c33dc8fe"
  },
  "fullName": "Hứa Thị Cẩm",
  "phone": "0912771885",
  "addressLine": "558 Đường 23",
  "city": "Vũng Tàu",
  "district": "Cầu Giấy",
  "ward": "Phường Quán Thánh",
  "isDefault": true,
  "createdAt": {
    "$date": "2024-11-22T00:11:58.680Z"
  },
  "updatedAt": {
    "$date": "2025-06-12T12:38:53.786Z"
  },
  "__v": 0
},
{
  "_id": {
    "$oid": "684aca5df3433021c33dcbfe"
  },
  "user": {
    "$oid": "684aca5df3433021c33dc8fe"
  },
  "fullName": "Hứa Thị Cẩm",
  "phone": "0912771885",
  "addressLine": "348 Đường 32",
  "city": "Vũng Tàu",
  "district": "Quận 3",
  "ward": "Phường Quán Thánh",
  "isDefault": false,
  "createdAt": {
    "$date": "2024-11-22T00:11:58.680Z"
  },
  "updatedAt": {
    "$date": "2025-06-12T12:38:53.786Z"
  },
  "__v": 0
},
{
  "_id": {
    "$oid": "684aca5df3433021c33dcbff"
  },
  "user": {
    "$oid": "684aca5df3433021c33dc8ff"
  },
  "fullName": "Tạ Văn Đức",
  "phone": "0953647849",
  "addressLine": "610 Đường 21",
  "city": "Hà Nội",
  "district": "Cầu Giấy",
  "ward": "Phường Quán Thánh",
  "isDefault": true,
  "createdAt": {
    "$date": "2024-12-18T17:41:56.517Z"
  },
  "updatedAt": {
    "$date": "2025-06-12T12:38:53.786Z"
  },
  "__v": 0
},
{
  "_id": {
    "$oid": "684aca5df3433021c33dcc00"
  },
  "user": {
    "$oid": "684aca5df3433021c33dc8ff"
  },
  "fullName": "Tạ Văn Đức",
  "phone": "0953647849",
  "addressLine": "612 Đường 1",
  "city": "Hà Nội",
  "district": "Quận 1",
  "ward": "Phường 3",
  "isDefault": false,
  "createdAt": {
    "$date": "2024-12-18T17:41:56.517Z"
  },
  "updatedAt": {
    "$date": "2025-06-12T12:38:53.786Z"
  },
  "__v": 0
},
{
  "_id": {
    "$oid": "684aca5df3433021c33dcc01"
  },
  "user": {
    "$oid": "684aca5df3433021c33dc900"
  },
  "fullName": "Lữ Thị Ê",
  "phone": "0944062628",
  "addressLine": "97 Đường 32",
  "city": "Đà Nẵng",
  "district": "Long Biên",
  "ward": "Phường 3",
  "isDefault": true,
  "createdAt": {
    "$date": "2025-04-23T04:08:29.186Z"
  },
  "updatedAt": {
    "$date": "2025-06-12T12:38:53.786Z"
  },
  "__v": 0
},
{
  "_id": {
    "$oid": "684aca5df3433021c33dcc02"
  },
  "user": {
    "$oid": "684aca5df3433021c33dc901"
  },
  "fullName": "Nghiêm Văn Phong",
  "phone": "0934237328",
  "addressLine": "470 Đường 47",
  "city": "Vũng Tàu",
  "district": "Ba Đình",
  "ward": "Phường Láng Thượng",
  "isDefault": true,
  "createdAt": {
    "$date": "2024-10-22T21:29:44.443Z"
  },
  "updatedAt": {
    "$date": "2025-06-12T12:38:53.786Z"
  },
  "__v": 0
},
{
  "_id": {
    "$oid": "684aca5df3433021c33dcc03"
  },
  "user": {
    "$oid": "684aca5df3433021c33dc901"
  },
  "fullName": "Nghiêm Văn Phong",
  "phone": "0934237328",
  "addressLine": "724 Đường 12",
  "city": "Cần Thơ",
  "district": "Ba Đình",
  "ward": "Phường Quán Thánh",
  "isDefault": false,
  "createdAt": {
    "$date": "2024-10-22T21:29:44.443Z"
  },
  "updatedAt": {
    "$date": "2025-06-12T12:38:53.786Z"
  },
  "__v": 0
},
{
  "_id": {
    "$oid": "684aca5df3433021c33dcc04"
  },
  "user": {
    "$oid": "684aca5df3433021c33dc902"
  },
  "fullName": "Ông Thị Giang",
  "phone": "0924348655",
  "addressLine": "6 Đường 28",
  "city": "Đà Nẵng",
  "district": "Ba Đình",
  "ward": "Phường 3",
  "isDefault": true,
  "createdAt": {
    "$date": "2025-01-05T21:44:37.916Z"
  },
  "updatedAt": {
    "$date": "2025-06-12T12:38:53.786Z"
  },
  "__v": 0
},
{
  "_id": {
    "$oid": "684aca5df3433021c33dcc05"
  },
  "user": {
    "$oid": "684aca5df3433021c33dc903"
  },
  "fullName": "Nguyễn Văn An",
  "phone": "0919499272",
  "addressLine": "621 Đường 20",
  "city": "Nha Trang",
  "district": "Hoàn Kiếm",
  "ward": "Phường 3",
  "isDefault": true,
  "createdAt": {
    "$date": "2024-12-22T03:34:41.996Z"
  },
  "updatedAt": {
    "$date": "2025-06-12T12:38:53.786Z"
  },
  "__v": 0
},
{
  "_id": {
    "$oid": "684aca5df3433021c33dcc06"
  },
  "user": {
    "$oid": "684aca5df3433021c33dc904"
  },
  "fullName": "Trần Thị Bình",
  "phone": "0978078453",
  "addressLine": "304 Đường 43",
  "city": "Nha Trang",
  "district": "Quận 2",
  "ward": "Phường 3",
  "isDefault": true,
  "createdAt": {
    "$date": "2024-11-21T13:49:21.715Z"
  },
  "updatedAt": {
    "$date": "2025-06-12T12:38:53.786Z"
  },
  "__v": 0
},
{
  "_id": {
    "$oid": "684aca5df3433021c33dcc07"
  },
  "user": {
    "$oid": "684aca5df3433021c33dc905"
  },
  "fullName": "Lê Hoàng Cường",
  "phone": "0926829594",
  "addressLine": "384 Đường 29",
  "city": "Vũng Tàu",
  "district": "Quận 3",
  "ward": "Phường Thành Công",
  "isDefault": true,
  "createdAt": {
    "$date": "2024-12-05T06:04:10.364Z"
  },
  "updatedAt": {
    "$date": "2025-06-12T12:38:53.786Z"
  },
  "__v": 0
},
{
  "_id": {
    "$oid": "684aca5df3433021c33dcc08"
  },
  "user": {
    "$oid": "684aca5df3433021c33dc906"
  },
  "fullName": "Phạm Thị Dương",
  "phone": "0922940801",
  "addressLine": "849 Đường 39",
  "city": "Nha Trang",
  "district": "Long Biên",
  "ward": "Phường Quán Thánh",
  "isDefault": true,
  "createdAt": {
    "$date": "2025-03-30T22:18:41.793Z"
  },
  "updatedAt": {
    "$date": "2025-06-12T12:38:53.786Z"
  },
  "__v": 0
},
{
  "_id": {
    "$oid": "684aca5df3433021c33dcc09"
  },
  "user": {
    "$oid": "684aca5df3433021c33dc906"
  },
  "fullName": "Phạm Thị Dương",
  "phone": "0922940801",
  "addressLine": "409 Đường 12",
  "city": "Vũng Tàu",
  "district": "Hoàn Kiếm",
  "ward": "Phường Quán Thánh",
  "isDefault": false,
  "createdAt": {
    "$date": "2025-03-30T22:18:41.793Z"
  },
  "updatedAt": {
    "$date": "2025-06-12T12:38:53.786Z"
  },
  "__v": 0
},
{
  "_id": {
    "$oid": "684aca5df3433021c33dcc0a"
  },
  "user": {
    "$oid": "684aca5df3433021c33dc907"
  },
  "fullName": "Hoàng Văn Em",
  "phone": "0981851658",
  "addressLine": "495 Đường 20",
  "city": "Nha Trang",
  "district": "Quận 2",
  "ward": "Phường Láng Thượng",
  "isDefault": true,
  "createdAt": {
    "$date": "2025-05-13T01:34:51.746Z"
  },
  "updatedAt": {
    "$date": "2025-06-12T12:38:53.786Z"
  },
  "__v": 0
},
{
  "_id": {
    "$oid": "684aca5df3433021c33dcc0b"
  },
  "user": {
    "$oid": "684aca5df3433021c33dc908"
  },
  "fullName": "Ngô Thị Phương",
  "phone": "0944511739",
  "addressLine": "985 Đường 1",
  "city": "Hải Phòng",
  "district": "Long Biên",
  "ward": "Phường 1",
  "isDefault": true,
  "createdAt": {
    "$date": "2024-12-08T01:42:24.163Z"
  },
  "updatedAt": {
    "$date": "2025-06-12T12:38:53.786Z"
  },
  "__v": 0
},
{
  "_id": {
    "$oid": "684aca5df3433021c33dcc0c"
  },
  "user": {
    "$oid": "684aca5df3433021c33dc909"
  },
  "fullName": "Đặng Văn Giang",
  "phone": "0917095401",
  "addressLine": "462 Đường 30",
  "city": "Cần Thơ",
  "district": "Ba Đình",
  "ward": "Phường Thành Công",
  "isDefault": true,
  "createdAt": {
    "$date": "2024-09-05T08:22:35.538Z"
  },
  "updatedAt": {
    "$date": "2025-06-12T12:38:53.786Z"
  },
  "__v": 0
},
{
  "_id": {
    "$oid": "684aca5df3433021c33dcc0d"
  },
  "user": {
    "$oid": "684aca5df3433021c33dc90a"
  },
  "fullName": "Bùi Thị Hương",
  "phone": "0999726288",
  "addressLine": "930 Đường 17",
  "city": "Cần Thơ",
  "district": "Quận 3",
  "ward": "Phường 3",
  "isDefault": true,
  "createdAt": {
    "$date": "2024-08-11T14:05:46.378Z"
  },
  "updatedAt": {
    "$date": "2025-06-12T12:38:53.786Z"
  },
  "__v": 0
},
{
  "_id": {
    "$oid": "684aca5df3433021c33dcc0e"
  },
  "user": {
    "$oid": "684aca5df3433021c33dc90b"
  },
  "fullName": "Vũ Văn Inh",
  "phone": "0973760857",
  "addressLine": "283 Đường 14",
  "city": "Huế",
  "district": "Quận 3",
  "ward": "Phường 1",
  "isDefault": true,
  "createdAt": {
    "$date": "2024-06-27T08:36:16.804Z"
  },
  "updatedAt": {
    "$date": "2025-06-12T12:38:53.786Z"
  },
  "__v": 0
},
{
  "_id": {
    "$oid": "684aca5df3433021c33dcc0f"
  },
  "user": {
    "$oid": "684aca5df3433021c33dc90b"
  },
  "fullName": "Vũ Văn Inh",
  "phone": "0973760857",
  "addressLine": "815 Đường 2",
  "city": "Hồ Chí Minh",
  "district": "Hai Bà Trưng",
  "ward": "Phường 1",
  "isDefault": false,
  "createdAt": {
    "$date": "2024-06-27T08:36:16.804Z"
  },
  "updatedAt": {
    "$date": "2025-06-12T12:38:53.786Z"
  },
  "__v": 0
},
{
  "_id": {
    "$oid": "684aca5df3433021c33dcc10"
  },
  "user": {
    "$oid": "684aca5df3433021c33dc90c"
  },
  "fullName": "Cao Thị Khánh",
  "phone": "0989495576",
  "addressLine": "492 Đường 14",
  "city": "Hải Phòng",
  "district": "Cầu Giấy",
  "ward": "Phường 3",
  "isDefault": true,
  "createdAt": {
    "$date": "2024-10-05T23:25:12.447Z"
  },
  "updatedAt": {
    "$date": "2025-06-12T12:38:53.786Z"
  },
  "__v": 0
},
{
  "_id": {
    "$oid": "684aca5df3433021c33dcc11"
  },
  "user": {
    "$oid": "684aca5df3433021c33dc90c"
  },
  "fullName": "Cao Thị Khánh",
  "phone": "0989495576",
  "addressLine": "633 Đường 39",
  "city": "Nha Trang",
  "district": "Quận 1",
  "ward": "Phường 2",
  "isDefault": false,
  "createdAt": {
    "$date": "2024-10-05T23:25:12.447Z"
  },
  "updatedAt": {
    "$date": "2025-06-12T12:38:53.786Z"
  },
  "__v": 0
},
{
  "_id": {
    "$oid": "684aca5df3433021c33dcc12"
  },
  "user": {
    "$oid": "684aca5df3433021c33dc90d"
  },
  "fullName": "Đỗ Văn Long",
  "phone": "0971838895",
  "addressLine": "888 Đường 39",
  "city": "Hồ Chí Minh",
  "district": "Cầu Giấy",
  "ward": "Phường Quán Thánh",
  "isDefault": true,
  "createdAt": {
    "$date": "2025-03-12T22:58:58.853Z"
  },
  "updatedAt": {
    "$date": "2025-06-12T12:38:53.786Z"
  },
  "__v": 0
},
{
  "_id": {
    "$oid": "684aca5df3433021c33dcc13"
  },
  "user": {
    "$oid": "684aca5df3433021c33dc90d"
  },
  "fullName": "Đỗ Văn Long",
  "phone": "0971838895",
  "addressLine": "325 Đường 44",
  "city": "Hồ Chí Minh",
  "district": "Cầu Giấy",
  "ward": "Phường 2",
  "isDefault": false,
  "createdAt": {
    "$date": "2025-03-12T22:58:58.853Z"
  },
  "updatedAt": {
    "$date": "2025-06-12T12:38:53.786Z"
  },
  "__v": 0
},
{
  "_id": {
    "$oid": "684aca5df3433021c33dcc14"
  },
  "user": {
    "$oid": "684aca5df3433021c33dc90e"
  },
  "fullName": "Lý Thị Minh",
  "phone": "0976536535",
  "addressLine": "366 Đường 18",
  "city": "Đà Nẵng",
  "district": "Quận 2",
  "ward": "Phường 1",
  "isDefault": true,
  "createdAt": {
    "$date": "2025-02-26T22:14:14.664Z"
  },
  "updatedAt": {
    "$date": "2025-06-12T12:38:53.786Z"
  },
  "__v": 0
},
{
  "_id": {
    "$oid": "684aca5df3433021c33dcc15"
  },
  "user": {
    "$oid": "684aca5df3433021c33dc90f"
  },
  "fullName": "Tôn Văn Nam",
  "phone": "0924164632",
  "addressLine": "109 Đường 47",
  "city": "Nha Trang",
  "district": "Quận 3",
  "ward": "Phường 1",
  "isDefault": true,
  "createdAt": {
    "$date": "2025-02-10T16:50:53.584Z"
  },
  "updatedAt": {
    "$date": "2025-06-12T12:38:53.786Z"
  },
  "__v": 0
},
{
  "_id": {
    "$oid": "684aca5df3433021c33dcc16"
  },
  "user": {
    "$oid": "684aca5df3433021c33dc910"
  },
  "fullName": "Phan Thị Oanh",
  "phone": "0969940783",
  "addressLine": "352 Đường 8",
  "city": "Huế",
  "district": "Cầu Giấy",
  "ward": "Phường 3",
  "isDefault": true,
  "createdAt": {
    "$date": "2025-05-11T11:56:30.931Z"
  },
  "updatedAt": {
    "$date": "2025-06-12T12:38:53.786Z"
  },
  "__v": 0
},
{
  "_id": {
    "$oid": "684aca5df3433021c33dcc17"
  },
  "user": {
    "$oid": "684aca5df3433021c33dc911"
  },
  "fullName": "Đinh Văn Phúc",
  "phone": "0975758853",
  "addressLine": "32 Đường 14",
  "city": "Cần Thơ",
  "district": "Hai Bà Trưng",
  "ward": "Phường Láng Thượng",
  "isDefault": true,
  "createdAt": {
    "$date": "2025-03-28T21:21:54.062Z"
  },
  "updatedAt": {
    "$date": "2025-06-12T12:38:53.786Z"
  },
  "__v": 0
},
{
  "_id": {
    "$oid": "684aca5df3433021c33dcc18"
  },
  "user": {
    "$oid": "684aca5df3433021c33dc911"
  },
  "fullName": "Đinh Văn Phúc",
  "phone": "0975758853",
  "addressLine": "767 Đường 12",
  "city": "Hà Nội",
  "district": "Quận 3",
  "ward": "Phường 3",
  "isDefault": false,
  "createdAt": {
    "$date": "2025-03-28T21:21:54.062Z"
  },
  "updatedAt": {
    "$date": "2025-06-12T12:38:53.786Z"
  },
  "__v": 0
},
{
  "_id": {
    "$oid": "684aca5df3433021c33dcc19"
  },
  "user": {
    "$oid": "684aca5df3433021c33dc912"
  },
  "fullName": "Võ Thị Quỳnh",
  "phone": "0976145071",
  "addressLine": "965 Đường 39",
  "city": "Cần Thơ",
  "district": "Quận 3",
  "ward": "Phường 2",
  "isDefault": true,
  "createdAt": {
    "$date": "2024-10-22T11:21:25.838Z"
  },
  "updatedAt": {
    "$date": "2025-06-12T12:38:53.786Z"
  },
  "__v": 0
},
{
  "_id": {
    "$oid": "684aca5df3433021c33dcc1a"
  },
  "user": {
    "$oid": "684aca5df3433021c33dc913"
  },
  "fullName": "Dương Văn Sơn",
  "phone": "0989593003",
  "addressLine": "266 Đường 8",
  "city": "Đà Nẵng",
  "district": "Quận 3",
  "ward": "Phường 2",
  "isDefault": true,
  "createdAt": {
    "$date": "2024-10-05T06:35:31.546Z"
  },
  "updatedAt": {
    "$date": "2025-06-12T12:38:53.786Z"
  },
  "__v": 0
},
{
  "_id": {
    "$oid": "684aca5df3433021c33dcc1b"
  },
  "user": {
    "$oid": "684aca5df3433021c33dc914"
  },
  "fullName": "Chu Thị Tâm",
  "phone": "0979205729",
  "addressLine": "656 Đường 36",
  "city": "Cần Thơ",
  "district": "Long Biên",
  "ward": "Phường 2",
  "isDefault": true,
  "createdAt": {
    "$date": "2025-02-02T23:27:17.348Z"
  },
  "updatedAt": {
    "$date": "2025-06-12T12:38:53.786Z"
  },
  "__v": 0
},
{
  "_id": {
    "$oid": "684aca5df3433021c33dcc1c"
  },
  "user": {
    "$oid": "684aca5df3433021c33dc914"
  },
  "fullName": "Chu Thị Tâm",
  "phone": "0979205729",
  "addressLine": "300 Đường 29",
  "city": "Đà Nẵng",
  "district": "Quận 3",
  "ward": "Phường 1",
  "isDefault": false,
  "createdAt": {
    "$date": "2025-02-02T23:27:17.348Z"
  },
  "updatedAt": {
    "$date": "2025-06-12T12:38:53.786Z"
  },
  "__v": 0
},
{
  "_id": {
    "$oid": "684aca5df3433021c33dcc1d"
  },
  "user": {
    "$oid": "684aca5df3433021c33dc915"
  },
  "fullName": "Lưu Văn Ưng",
  "phone": "0940964352",
  "addressLine": "7 Đường 10",
  "city": "Hà Nội",
  "district": "Quận 3",
  "ward": "Phường 3",
  "isDefault": true,
  "createdAt": {
    "$date": "2024-08-03T22:39:27.944Z"
  },
  "updatedAt": {
    "$date": "2025-06-12T12:38:53.786Z"
  },
  "__v": 0
},
{
  "_id": {
    "$oid": "684aca5df3433021c33dcc1e"
  },
  "user": {
    "$oid": "684aca5df3433021c33dc915"
  },
  "fullName": "Lưu Văn Ưng",
  "phone": "0940964352",
  "addressLine": "654 Đường 11",
  "city": "Hồ Chí Minh",
  "district": "Quận 1",
  "ward": "Phường Thành Công",
  "isDefault": false,
  "createdAt": {
    "$date": "2024-08-03T22:39:27.944Z"
  },
  "updatedAt": {
    "$date": "2025-06-12T12:38:53.786Z"
  },
  "__v": 0
},
{
  "_id": {
    "$oid": "684aca5df3433021c33dcc1f"
  },
  "user": {
    "$oid": "684aca5df3433021c33dc916"
  },
  "fullName": "Mai Thị Vân",
  "phone": "0915455528",
  "addressLine": "264 Đường 31",
  "city": "Huế",
  "district": "Ba Đình",
  "ward": "Phường Thành Công",
  "isDefault": true,
  "createdAt": {
    "$date": "2024-06-22T21:10:31.764Z"
  },
  "updatedAt": {
    "$date": "2025-06-12T12:38:53.786Z"
  },
  "__v": 0
},
{
  "_id": {
    "$oid": "684aca5df3433021c33dcc20"
  },
  "user": {
    "$oid": "684aca5df3433021c33dc916"
  },
  "fullName": "Mai Thị Vân",
  "phone": "0915455528",
  "addressLine": "67 Đường 13",
  "city": "Huế",
  "district": "Quận 3",
  "ward": "Phường 2",
  "isDefault": false,
  "createdAt": {
    "$date": "2024-06-22T21:10:31.764Z"
  },
  "updatedAt": {
    "$date": "2025-06-12T12:38:53.786Z"
  },
  "__v": 0
},
{
  "_id": {
    "$oid": "684aca5df3433021c33dcc21"
  },
  "user": {
    "$oid": "684aca5df3433021c33dc917"
  },
  "fullName": "Trịnh Văn Xuân",
  "phone": "0927141561",
  "addressLine": "968 Đường 27",
  "city": "Vũng Tàu",
  "district": "Quận 3",
  "ward": "Phường 3",
  "isDefault": true,
  "createdAt": {
    "$date": "2024-07-01T10:25:27.362Z"
  },
  "updatedAt": {
    "$date": "2025-06-12T12:38:53.786Z"
  },
  "__v": 0
},
{
  "_id": {
    "$oid": "684aca5df3433021c33dcc22"
  },
  "user": {
    "$oid": "684aca5df3433021c33dc917"
  },
  "fullName": "Trịnh Văn Xuân",
  "phone": "0927141561",
  "addressLine": "773 Đường 50",
  "city": "Huế",
  "district": "Quận 3",
  "ward": "Phường 3",
  "isDefault": false,
  "createdAt": {
    "$date": "2024-07-01T10:25:27.362Z"
  },
  "updatedAt": {
    "$date": "2025-06-12T12:38:53.786Z"
  },
  "__v": 0
},
{
  "_id": {
    "$oid": "684aca5df3433021c33dcc23"
  },
  "user": {
    "$oid": "684aca5df3433021c33dc918"
  },
  "fullName": "Hồ Thị Yến",
  "phone": "0920319797",
  "addressLine": "676 Đường 42",
  "city": "Hải Phòng",
  "district": "Quận 1",
  "ward": "Phường 3",
  "isDefault": true,
  "createdAt": {
    "$date": "2024-06-14T02:38:45.065Z"
  },
  "updatedAt": {
    "$date": "2025-06-12T12:38:53.786Z"
  },
  "__v": 0
},
{
  "_id": {
    "$oid": "684aca5df3433021c33dcc24"
  },
  "user": {
    "$oid": "684aca5df3433021c33dc918"
  },
  "fullName": "Hồ Thị Yến",
  "phone": "0920319797",
  "addressLine": "66 Đường 25",
  "city": "Vũng Tàu",
  "district": "Long Biên",
  "ward": "Phường Quán Thánh",
  "isDefault": false,
  "createdAt": {
    "$date": "2024-06-14T02:38:45.065Z"
  },
  "updatedAt": {
    "$date": "2025-06-12T12:38:53.786Z"
  },
  "__v": 0
},
{
  "_id": {
    "$oid": "684aca5df3433021c33dcc25"
  },
  "user": {
    "$oid": "684aca5df3433021c33dc919"
  },
  "fullName": "Lâm Văn Zung",
  "phone": "0965157061",
  "addressLine": "613 Đường 29",
  "city": "Hồ Chí Minh",
  "district": "Cầu Giấy",
  "ward": "Phường 3",
  "isDefault": true,
  "createdAt": {
    "$date": "2024-07-24T04:40:23.817Z"
  },
  "updatedAt": {
    "$date": "2025-06-12T12:38:53.786Z"
  },
  "__v": 0
},
{
  "_id": {
    "$oid": "684aca5df3433021c33dcc26"
  },
  "user": {
    "$oid": "684aca5df3433021c33dc919"
  },
  "fullName": "Lâm Văn Zung",
  "phone": "0965157061",
  "addressLine": "846 Đường 34",
  "city": "Vũng Tàu",
  "district": "Long Biên",
  "ward": "Phường 3",
  "isDefault": false,
  "createdAt": {
    "$date": "2024-07-24T04:40:23.817Z"
  },
  "updatedAt": {
    "$date": "2025-06-12T12:38:53.786Z"
  },
  "__v": 0
},
{
  "_id": {
    "$oid": "684aca5df3433021c33dcc27"
  },
  "user": {
    "$oid": "684aca5df3433021c33dc91a"
  },
  "fullName": "Từ Thị Ánh",
  "phone": "0922357926",
  "addressLine": "593 Đường 1",
  "city": "Hồ Chí Minh",
  "district": "Quận 3",
  "ward": "Phường Quán Thánh",
  "isDefault": true,
  "createdAt": {
    "$date": "2024-12-03T11:58:41.720Z"
  },
  "updatedAt": {
    "$date": "2025-06-12T12:38:53.786Z"
  },
  "__v": 0
},
{
  "_id": {
    "$oid": "684aca5df3433021c33dcc28"
  },
  "user": {
    "$oid": "684aca5df3433021c33dc91a"
  },
  "fullName": "Từ Thị Ánh",
  "phone": "0922357926",
  "addressLine": "521 Đường 14",
  "city": "Huế",
  "district": "Long Biên",
  "ward": "Phường 1",
  "isDefault": false,
  "createdAt": {
    "$date": "2024-12-03T11:58:41.720Z"
  },
  "updatedAt": {
    "$date": "2025-06-12T12:38:53.786Z"
  },
  "__v": 0
},
{
  "_id": {
    "$oid": "684aca5df3433021c33dcc29"
  },
  "user": {
    "$oid": "684aca5df3433021c33dc91b"
  },
  "fullName": "Quan Văn Bảo",
  "phone": "0983094761",
  "addressLine": "268 Đường 49",
  "city": "Nha Trang",
  "district": "Cầu Giấy",
  "ward": "Phường 2",
  "isDefault": true,
  "createdAt": {
    "$date": "2025-05-16T22:37:26.468Z"
  },
  "updatedAt": {
    "$date": "2025-06-12T12:38:53.786Z"
  },
  "__v": 0
},
{
  "_id": {
    "$oid": "684aca5df3433021c33dcc2a"
  },
  "user": {
    "$oid": "684aca5df3433021c33dc91c"
  },
  "fullName": "Hứa Thị Cẩm",
  "phone": "0927364334",
  "addressLine": "954 Đường 44",
  "city": "Hà Nội",
  "district": "Hai Bà Trưng",
  "ward": "Phường Thành Công",
  "isDefault": true,
  "createdAt": {
    "$date": "2024-08-20T21:21:05.846Z"
  },
  "updatedAt": {
    "$date": "2025-06-12T12:38:53.786Z"
  },
  "__v": 0
},
{
  "_id": {
    "$oid": "684aca5df3433021c33dcc2b"
  },
  "user": {
    "$oid": "684aca5df3433021c33dc91c"
  },
  "fullName": "Hứa Thị Cẩm",
  "phone": "0927364334",
  "addressLine": "436 Đường 32",
  "city": "Cần Thơ",
  "district": "Cầu Giấy",
  "ward": "Phường Quán Thánh",
  "isDefault": false,
  "createdAt": {
    "$date": "2024-08-20T21:21:05.846Z"
  },
  "updatedAt": {
    "$date": "2025-06-12T12:38:53.786Z"
  },
  "__v": 0
},
{
  "_id": {
    "$oid": "684aca5df3433021c33dcc2c"
  },
  "user": {
    "$oid": "684aca5df3433021c33dc91d"
  },
  "fullName": "Tạ Văn Đức",
  "phone": "0981534510",
  "addressLine": "871 Đường 9",
  "city": "Đà Nẵng",
  "district": "Ba Đình",
  "ward": "Phường 1",
  "isDefault": true,
  "createdAt": {
    "$date": "2024-10-02T16:07:26.833Z"
  },
  "updatedAt": {
    "$date": "2025-06-12T12:38:53.786Z"
  },
  "__v": 0
},
{
  "_id": {
    "$oid": "684aca5df3433021c33dcc2d"
  },
  "user": {
    "$oid": "684aca5df3433021c33dc91d"
  },
  "fullName": "Tạ Văn Đức",
  "phone": "0981534510",
  "addressLine": "473 Đường 16",
  "city": "Vũng Tàu",
  "district": "Long Biên",
  "ward": "Phường Quán Thánh",
  "isDefault": false,
  "createdAt": {
    "$date": "2024-10-02T16:07:26.833Z"
  },
  "updatedAt": {
    "$date": "2025-06-12T12:38:53.786Z"
  },
  "__v": 0
},
{
  "_id": {
    "$oid": "684aca5df3433021c33dcc2e"
  },
  "user": {
    "$oid": "684aca5df3433021c33dc91e"
  },
  "fullName": "Lữ Thị Ê",
  "phone": "0946650505",
  "addressLine": "50 Đường 35",
  "city": "Vũng Tàu",
  "district": "Cầu Giấy",
  "ward": "Phường 1",
  "isDefault": true,
  "createdAt": {
    "$date": "2024-08-23T06:44:15.289Z"
  },
  "updatedAt": {
    "$date": "2025-06-12T12:38:53.786Z"
  },
  "__v": 0
},
{
  "_id": {
    "$oid": "684aca5df3433021c33dcc2f"
  },
  "user": {
    "$oid": "684aca5df3433021c33dc91e"
  },
  "fullName": "Lữ Thị Ê",
  "phone": "0946650505",
  "addressLine": "845 Đường 46",
  "city": "Hồ Chí Minh",
  "district": "Ba Đình",
  "ward": "Phường 3",
  "isDefault": false,
  "createdAt": {
    "$date": "2024-08-23T06:44:15.289Z"
  },
  "updatedAt": {
    "$date": "2025-06-12T12:38:53.786Z"
  },
  "__v": 0
},
{
  "_id": {
    "$oid": "684aca5df3433021c33dcc30"
  },
  "user": {
    "$oid": "684aca5df3433021c33dc91f"
  },
  "fullName": "Nghiêm Văn Phong",
  "phone": "0947918757",
  "addressLine": "549 Đường 1",
  "city": "Hồ Chí Minh",
  "district": "Quận 3",
  "ward": "Phường Thành Công",
  "isDefault": true,
  "createdAt": {
    "$date": "2024-12-19T01:53:40.402Z"
  },
  "updatedAt": {
    "$date": "2025-06-12T12:38:53.786Z"
  },
  "__v": 0
},
{
  "_id": {
    "$oid": "684aca5df3433021c33dcc31"
  },
  "user": {
    "$oid": "684aca5df3433021c33dc920"
  },
  "fullName": "Ông Thị Giang",
  "phone": "0986482279",
  "addressLine": "256 Đường 33",
  "city": "Hồ Chí Minh",
  "district": "Hoàn Kiếm",
  "ward": "Phường Thành Công",
  "isDefault": true,
  "createdAt": {
    "$date": "2024-09-13T00:47:01.255Z"
  },
  "updatedAt": {
    "$date": "2025-06-12T12:38:53.786Z"
  },
  "__v": 0
},
{
  "_id": {
    "$oid": "684aca5df3433021c33dcc32"
  },
  "user": {
    "$oid": "684aca5df3433021c33dc920"
  },
  "fullName": "Ông Thị Giang",
  "phone": "0986482279",
  "addressLine": "30 Đường 49",
  "city": "Cần Thơ",
  "district": "Cầu Giấy",
  "ward": "Phường Quán Thánh",
  "isDefault": false,
  "createdAt": {
    "$date": "2024-09-13T00:47:01.255Z"
  },
  "updatedAt": {
    "$date": "2025-06-12T12:38:53.786Z"
  },
  "__v": 0
},
{
  "_id": {
    "$oid": "684aca5df3433021c33dcc33"
  },
  "user": {
    "$oid": "684aca5df3433021c33dc921"
  },
  "fullName": "Nguyễn Văn An",
  "phone": "0918084072",
  "addressLine": "586 Đường 27",
  "city": "Hà Nội",
  "district": "Cầu Giấy",
  "ward": "Phường 2",
  "isDefault": true,
  "createdAt": {
    "$date": "2025-03-11T12:07:30.921Z"
  },
  "updatedAt": {
    "$date": "2025-06-12T12:38:53.786Z"
  },
  "__v": 0
},
{
  "_id": {
    "$oid": "684aca5df3433021c33dcc34"
  },
  "user": {
    "$oid": "684aca5df3433021c33dc921"
  },
  "fullName": "Nguyễn Văn An",
  "phone": "0918084072",
  "addressLine": "81 Đường 19",
  "city": "Vũng Tàu",
  "district": "Hai Bà Trưng",
  "ward": "Phường 1",
  "isDefault": false,
  "createdAt": {
    "$date": "2025-03-11T12:07:30.921Z"
  },
  "updatedAt": {
    "$date": "2025-06-12T12:38:53.786Z"
  },
  "__v": 0
},
{
  "_id": {
    "$oid": "684aca5df3433021c33dcc35"
  },
  "user": {
    "$oid": "684aca5df3433021c33dc922"
  },
  "fullName": "Trần Thị Bình",
  "phone": "0913535237",
  "addressLine": "177 Đường 44",
  "city": "Vũng Tàu",
  "district": "Quận 1",
  "ward": "Phường 1",
  "isDefault": true,
  "createdAt": {
    "$date": "2025-05-12T01:25:40.012Z"
  },
  "updatedAt": {
    "$date": "2025-06-12T12:38:53.786Z"
  },
  "__v": 0
},
{
  "_id": {
    "$oid": "684aca5df3433021c33dcc36"
  },
  "user": {
    "$oid": "684aca5df3433021c33dc922"
  },
  "fullName": "Trần Thị Bình",
  "phone": "0913535237",
  "addressLine": "628 Đường 21",
  "city": "Hồ Chí Minh",
  "district": "Ba Đình",
  "ward": "Phường Láng Thượng",
  "isDefault": false,
  "createdAt": {
    "$date": "2025-05-12T01:25:40.012Z"
  },
  "updatedAt": {
    "$date": "2025-06-12T12:38:53.786Z"
  },
  "__v": 0
},
{
  "_id": {
    "$oid": "684aca5df3433021c33dcc37"
  },
  "user": {
    "$oid": "684aca5df3433021c33dc923"
  },
  "fullName": "Lê Hoàng Cường",
  "phone": "0925614672",
  "addressLine": "5 Đường 10",
  "city": "Hà Nội",
  "district": "Quận 1",
  "ward": "Phường Quán Thánh",
  "isDefault": true,
  "createdAt": {
    "$date": "2025-02-01T01:10:32.193Z"
  },
  "updatedAt": {
    "$date": "2025-06-12T12:38:53.786Z"
  },
  "__v": 0
},
{
  "_id": {
    "$oid": "684aca5df3433021c33dcc38"
  },
  "user": {
    "$oid": "684aca5df3433021c33dc923"
  },
  "fullName": "Lê Hoàng Cường",
  "phone": "0925614672",
  "addressLine": "485 Đường 22",
  "city": "Đà Nẵng",
  "district": "Quận 2",
  "ward": "Phường 1",
  "isDefault": false,
  "createdAt": {
    "$date": "2025-02-01T01:10:32.193Z"
  },
  "updatedAt": {
    "$date": "2025-06-12T12:38:53.786Z"
  },
  "__v": 0
},
{
  "_id": {
    "$oid": "684aca5df3433021c33dcc39"
  },
  "user": {
    "$oid": "684aca5df3433021c33dc924"
  },
  "fullName": "Phạm Thị Dương",
  "phone": "0910669495",
  "addressLine": "560 Đường 21",
  "city": "Hải Phòng",
  "district": "Cầu Giấy",
  "ward": "Phường Thành Công",
  "isDefault": true,
  "createdAt": {
    "$date": "2025-03-13T07:17:41.131Z"
  },
  "updatedAt": {
    "$date": "2025-06-12T12:38:53.786Z"
  },
  "__v": 0
},
{
  "_id": {
    "$oid": "684aca5df3433021c33dcc3a"
  },
  "user": {
    "$oid": "684aca5df3433021c33dc925"
  },
  "fullName": "Hoàng Văn Em",
  "phone": "0952888272",
  "addressLine": "972 Đường 6",
  "city": "Cần Thơ",
  "district": "Long Biên",
  "ward": "Phường Thành Công",
  "isDefault": true,
  "createdAt": {
    "$date": "2024-08-24T07:33:05.058Z"
  },
  "updatedAt": {
    "$date": "2025-06-12T12:38:53.786Z"
  },
  "__v": 0
},
{
  "_id": {
    "$oid": "684aca5df3433021c33dcc3b"
  },
  "user": {
    "$oid": "684aca5df3433021c33dc925"
  },
  "fullName": "Hoàng Văn Em",
  "phone": "0952888272",
  "addressLine": "196 Đường 8",
  "city": "Hồ Chí Minh",
  "district": "Hoàn Kiếm",
  "ward": "Phường Láng Thượng",
  "isDefault": false,
  "createdAt": {
    "$date": "2024-08-24T07:33:05.058Z"
  },
  "updatedAt": {
    "$date": "2025-06-12T12:38:53.786Z"
  },
  "__v": 0
},
{
  "_id": {
    "$oid": "684aca5df3433021c33dcc3c"
  },
  "user": {
    "$oid": "684aca5df3433021c33dc926"
  },
  "fullName": "Ngô Thị Phương",
  "phone": "0972600607",
  "addressLine": "654 Đường 25",
  "city": "Nha Trang",
  "district": "Cầu Giấy",
  "ward": "Phường Láng Thượng",
  "isDefault": true,
  "createdAt": {
    "$date": "2025-05-06T12:23:58.449Z"
  },
  "updatedAt": {
    "$date": "2025-06-12T12:38:53.786Z"
  },
  "__v": 0
},
{
  "_id": {
    "$oid": "684aca5df3433021c33dcc3d"
  },
  "user": {
    "$oid": "684aca5df3433021c33dc927"
  },
  "fullName": "Đặng Văn Giang",
  "phone": "0914096175",
  "addressLine": "89 Đường 23",
  "city": "Vũng Tàu",
  "district": "Quận 1",
  "ward": "Phường Thành Công",
  "isDefault": true,
  "createdAt": {
    "$date": "2025-04-06T04:24:41.151Z"
  },
  "updatedAt": {
    "$date": "2025-06-12T12:38:53.786Z"
  },
  "__v": 0
},
{
  "_id": {
    "$oid": "684aca5df3433021c33dcc3e"
  },
  "user": {
    "$oid": "684aca5df3433021c33dc927"
  },
  "fullName": "Đặng Văn Giang",
  "phone": "0914096175",
  "addressLine": "166 Đường 10",
  "city": "Đà Nẵng",
  "district": "Hai Bà Trưng",
  "ward": "Phường 3",
  "isDefault": false,
  "createdAt": {
    "$date": "2025-04-06T04:24:41.151Z"
  },
  "updatedAt": {
    "$date": "2025-06-12T12:38:53.786Z"
  },
  "__v": 0
},
{
  "_id": {
    "$oid": "684aca5df3433021c33dcc3f"
  },
  "user": {
    "$oid": "684aca5df3433021c33dc928"
  },
  "fullName": "Bùi Thị Hương",
  "phone": "0910181162",
  "addressLine": "265 Đường 17",
  "city": "Vũng Tàu",
  "district": "Quận 3",
  "ward": "Phường 1",
  "isDefault": true,
  "createdAt": {
    "$date": "2024-06-21T00:41:08.940Z"
  },
  "updatedAt": {
    "$date": "2025-06-12T12:38:53.786Z"
  },
  "__v": 0
},
{
  "_id": {
    "$oid": "684aca5df3433021c33dcc40"
  },
  "user": {
    "$oid": "684aca5df3433021c33dc928"
  },
  "fullName": "Bùi Thị Hương",
  "phone": "0910181162",
  "addressLine": "233 Đường 29",
  "city": "Vũng Tàu",
  "district": "Hai Bà Trưng",
  "ward": "Phường Thành Công",
  "isDefault": false,
  "createdAt": {
    "$date": "2024-06-21T00:41:08.940Z"
  },
  "updatedAt": {
    "$date": "2025-06-12T12:38:53.787Z"
  },
  "__v": 0
},
{
  "_id": {
    "$oid": "684aca5df3433021c33dcc41"
  },
  "user": {
    "$oid": "684aca5df3433021c33dc929"
  },
  "fullName": "Vũ Văn Inh",
  "phone": "0999696326",
  "addressLine": "528 Đường 42",
  "city": "Cần Thơ",
  "district": "Hai Bà Trưng",
  "ward": "Phường Quán Thánh",
  "isDefault": true,
  "createdAt": {
    "$date": "2025-05-18T15:30:02.153Z"
  },
  "updatedAt": {
    "$date": "2025-06-12T12:38:53.787Z"
  },
  "__v": 0
},
{
  "_id": {
    "$oid": "684aca5df3433021c33dcc42"
  },
  "user": {
    "$oid": "684aca5df3433021c33dc92a"
  },
  "fullName": "Cao Thị Khánh",
  "phone": "0930829392",
  "addressLine": "975 Đường 26",
  "city": "Hà Nội",
  "district": "Hoàn Kiếm",
  "ward": "Phường Quán Thánh",
  "isDefault": true,
  "createdAt": {
    "$date": "2024-08-24T22:07:21.837Z"
  },
  "updatedAt": {
    "$date": "2025-06-12T12:38:53.787Z"
  },
  "__v": 0
},
{
  "_id": {
    "$oid": "684aca5df3433021c33dcc43"
  },
  "user": {
    "$oid": "684aca5df3433021c33dc92b"
  },
  "fullName": "Đỗ Văn Long",
  "phone": "0931729420",
  "addressLine": "918 Đường 22",
  "city": "Vũng Tàu",
  "district": "Hai Bà Trưng",
  "ward": "Phường 2",
  "isDefault": true,
  "createdAt": {
    "$date": "2024-08-15T13:31:24.013Z"
  },
  "updatedAt": {
    "$date": "2025-06-12T12:38:53.787Z"
  },
  "__v": 0
},
{
  "_id": {
    "$oid": "684aca5df3433021c33dcc44"
  },
  "user": {
    "$oid": "684aca5df3433021c33dc92b"
  },
  "fullName": "Đỗ Văn Long",
  "phone": "0931729420",
  "addressLine": "599 Đường 42",
  "city": "Hải Phòng",
  "district": "Quận 1",
  "ward": "Phường Thành Công",
  "isDefault": false,
  "createdAt": {
    "$date": "2024-08-15T13:31:24.013Z"
  },
  "updatedAt": {
    "$date": "2025-06-12T12:38:53.787Z"
  },
  "__v": 0
},
{
  "_id": {
    "$oid": "684aca5df3433021c33dcc45"
  },
  "user": {
    "$oid": "684aca5df3433021c33dc92c"
  },
  "fullName": "Lý Thị Minh",
  "phone": "0941370907",
  "addressLine": "692 Đường 39",
  "city": "Nha Trang",
  "district": "Quận 1",
  "ward": "Phường Quán Thánh",
  "isDefault": true,
  "createdAt": {
    "$date": "2024-08-10T01:57:56.864Z"
  },
  "updatedAt": {
    "$date": "2025-06-12T12:38:53.787Z"
  },
  "__v": 0
},
{
  "_id": {
    "$oid": "684aca5df3433021c33dcc46"
  },
  "user": {
    "$oid": "684aca5df3433021c33dc92c"
  },
  "fullName": "Lý Thị Minh",
  "phone": "0941370907",
  "addressLine": "926 Đường 34",
  "city": "Hồ Chí Minh",
  "district": "Hai Bà Trưng",
  "ward": "Phường Láng Thượng",
  "isDefault": false,
  "createdAt": {
    "$date": "2024-08-10T01:57:56.864Z"
  },
  "updatedAt": {
    "$date": "2025-06-12T12:38:53.787Z"
  },
  "__v": 0
},
{
  "_id": {
    "$oid": "684aca5df3433021c33dcc47"
  },
  "user": {
    "$oid": "684aca5df3433021c33dc92d"
  },
  "fullName": "Tôn Văn Nam",
  "phone": "0993993011",
  "addressLine": "951 Đường 29",
  "city": "Nha Trang",
  "district": "Ba Đình",
  "ward": "Phường 1",
  "isDefault": true,
  "createdAt": {
    "$date": "2024-08-27T18:21:50.698Z"
  },
  "updatedAt": {
    "$date": "2025-06-12T12:38:53.787Z"
  },
  "__v": 0
},
{
  "_id": {
    "$oid": "684aca5df3433021c33dcc48"
  },
  "user": {
    "$oid": "684aca5df3433021c33dc92e"
  },
  "fullName": "Phan Thị Oanh",
  "phone": "0997677821",
  "addressLine": "679 Đường 39",
  "city": "Hồ Chí Minh",
  "district": "Cầu Giấy",
  "ward": "Phường 3",
  "isDefault": true,
  "createdAt": {
    "$date": "2025-01-29T02:16:53.571Z"
  },
  "updatedAt": {
    "$date": "2025-06-12T12:38:53.787Z"
  },
  "__v": 0
},
{
  "_id": {
    "$oid": "684aca5df3433021c33dcc49"
  },
  "user": {
    "$oid": "684aca5df3433021c33dc92f"
  },
  "fullName": "Đinh Văn Phúc",
  "phone": "0913900226",
  "addressLine": "506 Đường 4",
  "city": "Huế",
  "district": "Quận 2",
  "ward": "Phường 2",
  "isDefault": true,
  "createdAt": {
    "$date": "2024-12-13T17:31:04.792Z"
  },
  "updatedAt": {
    "$date": "2025-06-12T12:38:53.787Z"
  },
  "__v": 0
},
{
  "_id": {
    "$oid": "684aca5df3433021c33dcc4a"
  },
  "user": {
    "$oid": "684aca5df3433021c33dc930"
  },
  "fullName": "Võ Thị Quỳnh",
  "phone": "0961711575",
  "addressLine": "856 Đường 22",
  "city": "Cần Thơ",
  "district": "Quận 3",
  "ward": "Phường 2",
  "isDefault": true,
  "createdAt": {
    "$date": "2024-07-26T23:20:04.850Z"
  },
  "updatedAt": {
    "$date": "2025-06-12T12:38:53.787Z"
  },
  "__v": 0
},
{
  "_id": {
    "$oid": "684aca5df3433021c33dcc4b"
  },
  "user": {
    "$oid": "684aca5df3433021c33dc930"
  },
  "fullName": "Võ Thị Quỳnh",
  "phone": "0961711575",
  "addressLine": "95 Đường 38",
  "city": "Hải Phòng",
  "district": "Ba Đình",
  "ward": "Phường 3",
  "isDefault": false,
  "createdAt": {
    "$date": "2024-07-26T23:20:04.850Z"
  },
  "updatedAt": {
    "$date": "2025-06-12T12:38:53.787Z"
  },
  "__v": 0
},
{
  "_id": {
    "$oid": "684aca5df3433021c33dcc4c"
  },
  "user": {
    "$oid": "684aca5df3433021c33dc931"
  },
  "fullName": "Dương Văn Sơn",
  "phone": "0944018294",
  "addressLine": "206 Đường 29",
  "city": "Đà Nẵng",
  "district": "Quận 2",
  "ward": "Phường 3",
  "isDefault": true,
  "createdAt": {
    "$date": "2024-09-21T22:29:04.500Z"
  },
  "updatedAt": {
    "$date": "2025-06-12T12:38:53.787Z"
  },
  "__v": 0
},
{
  "_id": {
    "$oid": "684aca5df3433021c33dcc4d"
  },
  "user": {
    "$oid": "684aca5df3433021c33dc932"
  },
  "fullName": "Chu Thị Tâm",
  "phone": "0928426844",
  "addressLine": "577 Đường 24",
  "city": "Hà Nội",
  "district": "Long Biên",
  "ward": "Phường 1",
  "isDefault": true,
  "createdAt": {
    "$date": "2025-04-02T21:35:28.585Z"
  },
  "updatedAt": {
    "$date": "2025-06-12T12:38:53.787Z"
  },
  "__v": 0
},
{
  "_id": {
    "$oid": "684aca5df3433021c33dcc4e"
  },
  "user": {
    "$oid": "684aca5df3433021c33dc932"
  },
  "fullName": "Chu Thị Tâm",
  "phone": "0928426844",
  "addressLine": "650 Đường 21",
  "city": "Huế",
  "district": "Cầu Giấy",
  "ward": "Phường Quán Thánh",
  "isDefault": false,
  "createdAt": {
    "$date": "2025-04-02T21:35:28.585Z"
  },
  "updatedAt": {
    "$date": "2025-06-12T12:38:53.787Z"
  },
  "__v": 0
},
{
  "_id": {
    "$oid": "684aca5df3433021c33dcc4f"
  },
  "user": {
    "$oid": "684aca5df3433021c33dc933"
  },
  "fullName": "Lưu Văn Ưng",
  "phone": "0912927353",
  "addressLine": "219 Đường 17",
  "city": "Vũng Tàu",
  "district": "Quận 3",
  "ward": "Phường Láng Thượng",
  "isDefault": true,
  "createdAt": {
    "$date": "2025-05-12T11:10:02.473Z"
  },
  "updatedAt": {
    "$date": "2025-06-12T12:38:53.787Z"
  },
  "__v": 0
},
{
  "_id": {
    "$oid": "684aca5df3433021c33dcc50"
  },
  "user": {
    "$oid": "684aca5df3433021c33dc934"
  },
  "fullName": "Mai Thị Vân",
  "phone": "0939853656",
  "addressLine": "161 Đường 38",
  "city": "Hồ Chí Minh",
  "district": "Cầu Giấy",
  "ward": "Phường Quán Thánh",
  "isDefault": true,
  "createdAt": {
    "$date": "2025-04-19T15:46:53.997Z"
  },
  "updatedAt": {
    "$date": "2025-06-12T12:38:53.787Z"
  },
  "__v": 0
},
{
  "_id": {
    "$oid": "684aca5df3433021c33dcc51"
  },
  "user": {
    "$oid": "684aca5df3433021c33dc935"
  },
  "fullName": "Trịnh Văn Xuân",
  "phone": "0961222219",
  "addressLine": "752 Đường 7",
  "city": "Cần Thơ",
  "district": "Hoàn Kiếm",
  "ward": "Phường 2",
  "isDefault": true,
  "createdAt": {
    "$date": "2025-05-13T22:43:22.261Z"
  },
  "updatedAt": {
    "$date": "2025-06-12T12:38:53.787Z"
  },
  "__v": 0
},
{
  "_id": {
    "$oid": "684aca5df3433021c33dcc52"
  },
  "user": {
    "$oid": "684aca5df3433021c33dc936"
  },
  "fullName": "Hồ Thị Yến",
  "phone": "0990656184",
  "addressLine": "879 Đường 26",
  "city": "Hải Phòng",
  "district": "Hoàn Kiếm",
  "ward": "Phường Quán Thánh",
  "isDefault": true,
  "createdAt": {
    "$date": "2024-11-11T10:51:28.151Z"
  },
  "updatedAt": {
    "$date": "2025-06-12T12:38:53.787Z"
  },
  "__v": 0
},
{
  "_id": {
    "$oid": "684aca5df3433021c33dcc53"
  },
  "user": {
    "$oid": "684aca5df3433021c33dc937"
  },
  "fullName": "Lâm Văn Zung",
  "phone": "0984863035",
  "addressLine": "368 Đường 6",
  "city": "Hải Phòng",
  "district": "Cầu Giấy",
  "ward": "Phường 1",
  "isDefault": true,
  "createdAt": {
    "$date": "2024-06-14T20:11:29.317Z"
  },
  "updatedAt": {
    "$date": "2025-06-12T12:38:53.787Z"
  },
  "__v": 0
},
{
  "_id": {
    "$oid": "684aca5df3433021c33dcc54"
  },
  "user": {
    "$oid": "684aca5df3433021c33dc937"
  },
  "fullName": "Lâm Văn Zung",
  "phone": "0984863035",
  "addressLine": "764 Đường 34",
  "city": "Hà Nội",
  "district": "Quận 1",
  "ward": "Phường 3",
  "isDefault": false,
  "createdAt": {
    "$date": "2024-06-14T20:11:29.317Z"
  },
  "updatedAt": {
    "$date": "2025-06-12T12:38:53.787Z"
  },
  "__v": 0
},
{
  "_id": {
    "$oid": "684aca5df3433021c33dcc55"
  },
  "user": {
    "$oid": "684aca5df3433021c33dc938"
  },
  "fullName": "Từ Thị Ánh",
  "phone": "0939345620",
  "addressLine": "580 Đường 34",
  "city": "Cần Thơ",
  "district": "Hai Bà Trưng",
  "ward": "Phường Thành Công",
  "isDefault": true,
  "createdAt": {
    "$date": "2024-09-29T16:43:18.826Z"
  },
  "updatedAt": {
    "$date": "2025-06-12T12:38:53.787Z"
  },
  "__v": 0
},
{
  "_id": {
    "$oid": "684aca5df3433021c33dcc56"
  },
  "user": {
    "$oid": "684aca5df3433021c33dc938"
  },
  "fullName": "Từ Thị Ánh",
  "phone": "0939345620",
  "addressLine": "23 Đường 24",
  "city": "Nha Trang",
  "district": "Quận 2",
  "ward": "Phường Thành Công",
  "isDefault": false,
  "createdAt": {
    "$date": "2024-09-29T16:43:18.826Z"
  },
  "updatedAt": {
    "$date": "2025-06-12T12:38:53.787Z"
  },
  "__v": 0
},
{
  "_id": {
    "$oid": "684aca5df3433021c33dcc57"
  },
  "user": {
    "$oid": "684aca5df3433021c33dc939"
  },
  "fullName": "Quan Văn Bảo",
  "phone": "0989686079",
  "addressLine": "562 Đường 12",
  "city": "Cần Thơ",
  "district": "Quận 2",
  "ward": "Phường 2",
  "isDefault": true,
  "createdAt": {
    "$date": "2025-02-02T18:33:38.823Z"
  },
  "updatedAt": {
    "$date": "2025-06-12T12:38:53.787Z"
  },
  "__v": 0
},
{
  "_id": {
    "$oid": "684aca5df3433021c33dcc58"
  },
  "user": {
    "$oid": "684aca5df3433021c33dc93a"
  },
  "fullName": "Hứa Thị Cẩm",
  "phone": "0940293644",
  "addressLine": "556 Đường 28",
  "city": "Đà Nẵng",
  "district": "Ba Đình",
  "ward": "Phường Thành Công",
  "isDefault": true,
  "createdAt": {
    "$date": "2024-08-31T05:36:59.256Z"
  },
  "updatedAt": {
    "$date": "2025-06-12T12:38:53.787Z"
  },
  "__v": 0
},
{
  "_id": {
    "$oid": "684aca5df3433021c33dcc59"
  },
  "user": {
    "$oid": "684aca5df3433021c33dc93a"
  },
  "fullName": "Hứa Thị Cẩm",
  "phone": "0940293644",
  "addressLine": "545 Đường 40",
  "city": "Cần Thơ",
  "district": "Ba Đình",
  "ward": "Phường 3",
  "isDefault": false,
  "createdAt": {
    "$date": "2024-08-31T05:36:59.256Z"
  },
  "updatedAt": {
    "$date": "2025-06-12T12:38:53.787Z"
  },
  "__v": 0
},
{
  "_id": {
    "$oid": "684aca5df3433021c33dcc5a"
  },
  "user": {
    "$oid": "684aca5df3433021c33dc93b"
  },
  "fullName": "Tạ Văn Đức",
  "phone": "0937978885",
  "addressLine": "80 Đường 39",
  "city": "Hải Phòng",
  "district": "Cầu Giấy",
  "ward": "Phường Quán Thánh",
  "isDefault": true,
  "createdAt": {
    "$date": "2024-09-10T07:43:44.372Z"
  },
  "updatedAt": {
    "$date": "2025-06-12T12:38:53.787Z"
  },
  "__v": 0
},
{
  "_id": {
    "$oid": "684aca5df3433021c33dcc5b"
  },
  "user": {
    "$oid": "684aca5df3433021c33dc93c"
  },
  "fullName": "Lữ Thị Ê",
  "phone": "0973772282",
  "addressLine": "336 Đường 25",
  "city": "Vũng Tàu",
  "district": "Quận 1",
  "ward": "Phường 2",
  "isDefault": true,
  "createdAt": {
    "$date": "2025-01-22T05:18:27.745Z"
  },
  "updatedAt": {
    "$date": "2025-06-12T12:38:53.787Z"
  },
  "__v": 0
},
{
  "_id": {
    "$oid": "684aca5df3433021c33dcc5c"
  },
  "user": {
    "$oid": "684aca5df3433021c33dc93d"
  },
  "fullName": "Nghiêm Văn Phong",
  "phone": "0953161248",
  "addressLine": "597 Đường 25",
  "city": "Đà Nẵng",
  "district": "Ba Đình",
  "ward": "Phường 3",
  "isDefault": true,
  "createdAt": {
    "$date": "2025-03-12T18:57:11.747Z"
  },
  "updatedAt": {
    "$date": "2025-06-12T12:38:53.787Z"
  },
  "__v": 0
},
{
  "_id": {
    "$oid": "684aca5df3433021c33dcc5d"
  },
  "user": {
    "$oid": "684aca5df3433021c33dc93e"
  },
  "fullName": "Ông Thị Giang",
  "phone": "0932152023",
  "addressLine": "885 Đường 19",
  "city": "Hồ Chí Minh",
  "district": "Hai Bà Trưng",
  "ward": "Phường 3",
  "isDefault": true,
  "createdAt": {
    "$date": "2024-10-18T15:53:19.146Z"
  },
  "updatedAt": {
    "$date": "2025-06-12T12:38:53.787Z"
  },
  "__v": 0
},
{
  "_id": {
    "$oid": "684aca5df3433021c33dcc5e"
  },
  "user": {
    "$oid": "684aca5df3433021c33dc93f"
  },
  "fullName": "Nguyễn Văn An",
  "phone": "0920095271",
  "addressLine": "137 Đường 11",
  "city": "Đà Nẵng",
  "district": "Quận 1",
  "ward": "Phường 3",
  "isDefault": true,
  "createdAt": {
    "$date": "2025-02-14T08:46:43.931Z"
  },
  "updatedAt": {
    "$date": "2025-06-12T12:38:53.787Z"
  },
  "__v": 0
},
{
  "_id": {
    "$oid": "684aca5df3433021c33dcc5f"
  },
  "user": {
    "$oid": "684aca5df3433021c33dc93f"
  },
  "fullName": "Nguyễn Văn An",
  "phone": "0920095271",
  "addressLine": "485 Đường 17",
  "city": "Nha Trang",
  "district": "Long Biên",
  "ward": "Phường Láng Thượng",
  "isDefault": false,
  "createdAt": {
    "$date": "2025-02-14T08:46:43.931Z"
  },
  "updatedAt": {
    "$date": "2025-06-12T12:38:53.787Z"
  },
  "__v": 0
},
{
  "_id": {
    "$oid": "684aca5df3433021c33dcc60"
  },
  "user": {
    "$oid": "684aca5df3433021c33dc940"
  },
  "fullName": "Trần Thị Bình",
  "phone": "0942831772",
  "addressLine": "934 Đường 6",
  "city": "Hải Phòng",
  "district": "Long Biên",
  "ward": "Phường 3",
  "isDefault": true,
  "createdAt": {
    "$date": "2024-09-06T08:05:18.329Z"
  },
  "updatedAt": {
    "$date": "2025-06-12T12:38:53.787Z"
  },
  "__v": 0
},
{
  "_id": {
    "$oid": "684aca5df3433021c33dcc61"
  },
  "user": {
    "$oid": "684aca5df3433021c33dc940"
  },
  "fullName": "Trần Thị Bình",
  "phone": "0942831772",
  "addressLine": "641 Đường 41",
  "city": "Hà Nội",
  "district": "Cầu Giấy",
  "ward": "Phường 1",
  "isDefault": false,
  "createdAt": {
    "$date": "2024-09-06T08:05:18.329Z"
  },
  "updatedAt": {
    "$date": "2025-06-12T12:38:53.787Z"
  },
  "__v": 0
},
{
  "_id": {
    "$oid": "684aca5df3433021c33dcc62"
  },
  "user": {
    "$oid": "684aca5df3433021c33dc941"
  },
  "fullName": "Lê Hoàng Cường",
  "phone": "0914438977",
  "addressLine": "421 Đường 13",
  "city": "Cần Thơ",
  "district": "Hai Bà Trưng",
  "ward": "Phường 3",
  "isDefault": true,
  "createdAt": {
    "$date": "2024-11-10T20:26:07.638Z"
  },
  "updatedAt": {
    "$date": "2025-06-12T12:38:53.787Z"
  },
  "__v": 0
},
{
  "_id": {
    "$oid": "684aca5df3433021c33dcc63"
  },
  "user": {
    "$oid": "684aca5df3433021c33dc942"
  },
  "fullName": "Phạm Thị Dương",
  "phone": "0928884818",
  "addressLine": "913 Đường 19",
  "city": "Vũng Tàu",
  "district": "Hoàn Kiếm",
  "ward": "Phường 3",
  "isDefault": true,
  "createdAt": {
    "$date": "2024-12-25T00:52:09.750Z"
  },
  "updatedAt": {
    "$date": "2025-06-12T12:38:53.787Z"
  },
  "__v": 0
},
{
  "_id": {
    "$oid": "684aca5df3433021c33dcc64"
  },
  "user": {
    "$oid": "684aca5df3433021c33dc943"
  },
  "fullName": "Hoàng Văn Em",
  "phone": "0984464010",
  "addressLine": "973 Đường 27",
  "city": "Cần Thơ",
  "district": "Cầu Giấy",
  "ward": "Phường Thành Công",
  "isDefault": true,
  "createdAt": {
    "$date": "2025-05-02T00:30:43.927Z"
  },
  "updatedAt": {
    "$date": "2025-06-12T12:38:53.787Z"
  },
  "__v": 0
},
{
  "_id": {
    "$oid": "684aca5df3433021c33dcc65"
  },
  "user": {
    "$oid": "684aca5df3433021c33dc944"
  },
  "fullName": "Ngô Thị Phương",
  "phone": "0923171956",
  "addressLine": "635 Đường 32",
  "city": "Hải Phòng",
  "district": "Quận 2",
  "ward": "Phường 1",
  "isDefault": true,
  "createdAt": {
    "$date": "2024-11-06T12:36:12.017Z"
  },
  "updatedAt": {
    "$date": "2025-06-12T12:38:53.787Z"
  },
  "__v": 0
},
{
  "_id": {
    "$oid": "684aca5df3433021c33dcc66"
  },
  "user": {
    "$oid": "684aca5df3433021c33dc944"
  },
  "fullName": "Ngô Thị Phương",
  "phone": "0923171956",
  "addressLine": "662 Đường 18",
  "city": "Nha Trang",
  "district": "Quận 3",
  "ward": "Phường 1",
  "isDefault": false,
  "createdAt": {
    "$date": "2024-11-06T12:36:12.017Z"
  },
  "updatedAt": {
    "$date": "2025-06-12T12:38:53.787Z"
  },
  "__v": 0
},
{
  "_id": {
    "$oid": "684aca5df3433021c33dcc67"
  },
  "user": {
    "$oid": "684aca5df3433021c33dc945"
  },
  "fullName": "Đặng Văn Giang",
  "phone": "0951124917",
  "addressLine": "417 Đường 8",
  "city": "Cần Thơ",
  "district": "Hai Bà Trưng",
  "ward": "Phường 1",
  "isDefault": true,
  "createdAt": {
    "$date": "2024-07-01T14:34:01.161Z"
  },
  "updatedAt": {
    "$date": "2025-06-12T12:38:53.787Z"
  },
  "__v": 0
},
{
  "_id": {
    "$oid": "684aca5df3433021c33dcc68"
  },
  "user": {
    "$oid": "684aca5df3433021c33dc945"
  },
  "fullName": "Đặng Văn Giang",
  "phone": "0951124917",
  "addressLine": "554 Đường 2",
  "city": "Nha Trang",
  "district": "Long Biên",
  "ward": "Phường 2",
  "isDefault": false,
  "createdAt": {
    "$date": "2024-07-01T14:34:01.161Z"
  },
  "updatedAt": {
    "$date": "2025-06-12T12:38:53.787Z"
  },
  "__v": 0
},
{
  "_id": {
    "$oid": "684aca5df3433021c33dcc69"
  },
  "user": {
    "$oid": "684aca5df3433021c33dc946"
  },
  "fullName": "Bùi Thị Hương",
  "phone": "0934937330",
  "addressLine": "310 Đường 3",
  "city": "Hồ Chí Minh",
  "district": "Cầu Giấy",
  "ward": "Phường 2",
  "isDefault": true,
  "createdAt": {
    "$date": "2025-06-08T18:15:31.038Z"
  },
  "updatedAt": {
    "$date": "2025-06-12T12:38:53.787Z"
  },
  "__v": 0
},
{
  "_id": {
    "$oid": "684aca5df3433021c33dcc6a"
  },
  "user": {
    "$oid": "684aca5df3433021c33dc946"
  },
  "fullName": "Bùi Thị Hương",
  "phone": "0934937330",
  "addressLine": "247 Đường 32",
  "city": "Huế",
  "district": "Quận 2",
  "ward": "Phường Láng Thượng",
  "isDefault": false,
  "createdAt": {
    "$date": "2025-06-08T18:15:31.038Z"
  },
  "updatedAt": {
    "$date": "2025-06-12T12:38:53.787Z"
  },
  "__v": 0
},
{
  "_id": {
    "$oid": "684aca5df3433021c33dcc6b"
  },
  "user": {
    "$oid": "684aca5df3433021c33dc947"
  },
  "fullName": "Vũ Văn Inh",
  "phone": "0975250672",
  "addressLine": "317 Đường 21",
  "city": "Hà Nội",
  "district": "Long Biên",
  "ward": "Phường Quán Thánh",
  "isDefault": true,
  "createdAt": {
    "$date": "2024-07-06T08:23:04.178Z"
  },
  "updatedAt": {
    "$date": "2025-06-12T12:38:53.787Z"
  },
  "__v": 0
},
{
  "_id": {
    "$oid": "684aca5df3433021c33dcc6c"
  },
  "user": {
    "$oid": "684aca5df3433021c33dc947"
  },
  "fullName": "Vũ Văn Inh",
  "phone": "0975250672",
  "addressLine": "650 Đường 6",
  "city": "Hà Nội",
  "district": "Long Biên",
  "ward": "Phường Thành Công",
  "isDefault": false,
  "createdAt": {
    "$date": "2024-07-06T08:23:04.178Z"
  },
  "updatedAt": {
    "$date": "2025-06-12T12:38:53.787Z"
  },
  "__v": 0
},
{
  "_id": {
    "$oid": "684aca5df3433021c33dcc6d"
  },
  "user": {
    "$oid": "684aca5df3433021c33dc948"
  },
  "fullName": "Cao Thị Khánh",
  "phone": "0990885469",
  "addressLine": "593 Đường 27",
  "city": "Cần Thơ",
  "district": "Hai Bà Trưng",
  "ward": "Phường Thành Công",
  "isDefault": true,
  "createdAt": {
    "$date": "2025-03-31T03:54:17.823Z"
  },
  "updatedAt": {
    "$date": "2025-06-12T12:38:53.787Z"
  },
  "__v": 0
},
{
  "_id": {
    "$oid": "684aca5df3433021c33dcc6e"
  },
  "user": {
    "$oid": "684aca5df3433021c33dc948"
  },
  "fullName": "Cao Thị Khánh",
  "phone": "0990885469",
  "addressLine": "540 Đường 5",
  "city": "Hà Nội",
  "district": "Ba Đình",
  "ward": "Phường 2",
  "isDefault": false,
  "createdAt": {
    "$date": "2025-03-31T03:54:17.823Z"
  },
  "updatedAt": {
    "$date": "2025-06-12T12:38:53.787Z"
  },
  "__v": 0
},
{
  "_id": {
    "$oid": "684aca5df3433021c33dcc6f"
  },
  "user": {
    "$oid": "684aca5df3433021c33dc949"
  },
  "fullName": "Đỗ Văn Long",
  "phone": "0944545699",
  "addressLine": "865 Đường 4",
  "city": "Đà Nẵng",
  "district": "Cầu Giấy",
  "ward": "Phường Láng Thượng",
  "isDefault": true,
  "createdAt": {
    "$date": "2024-11-07T17:24:15.372Z"
  },
  "updatedAt": {
    "$date": "2025-06-12T12:38:53.787Z"
  },
  "__v": 0
},
{
  "_id": {
    "$oid": "684aca5df3433021c33dcc70"
  },
  "user": {
    "$oid": "684aca5df3433021c33dc949"
  },
  "fullName": "Đỗ Văn Long",
  "phone": "0944545699",
  "addressLine": "691 Đường 34",
  "city": "Hải Phòng",
  "district": "Quận 2",
  "ward": "Phường 1",
  "isDefault": false,
  "createdAt": {
    "$date": "2024-11-07T17:24:15.372Z"
  },
  "updatedAt": {
    "$date": "2025-06-12T12:38:53.787Z"
  },
  "__v": 0
}]